{
  "lang": "C",
  "homepage": "https://github.com/FredHucht/pstree",
  "desc": {
    "cn": "pstree 是一个小程序，它将进程列表（ps）显示为树状",
    "en": "pstree is a small program that shows the process listing (ps) as a tree"
  },
  "rule": {
    "darwin/brew": {
      "cmd": "brew install pstree",
      "reference": "https://formulae.brew.sh/formula/pstree#default"
    },
    "debian/apt": {
      "cmd": "sudo apt-get install psmisc",
      "reference": "https://command-not-found.com/pstree",
      "dsnap": "psmisc"
    },
    "ubuntu/apt": {
      "cmd": "sudo apt-get install psmisc",
      "reference": "https://command-not-found.com/pstree",
      "dsnap": "psmisc"
    },
    "alpine/apk": {
      "cmd": "sudo apk add psmisc",
      "reference": "https://command-not-found.com/pstree",
      "dsnap": "psmisc"
    },
    "arch/pacman": {
      "cmd": "sudo pacman -S psmisc",
      "reference": "https://command-not-found.com/pstree"
    },
    "kali/apt": {
      "cmd": "sudo apt-get install psmisc",
      "reference": "https://command-not-found.com/pstree"
    },
    "centos/yum": {
      "cmd": "sudo yum install psmisc",
      "reference": "https://command-not-found.com/pstree"
    },
    "rhel/yum": {
      "cmd": "sudo yum install psmisc",
      "reference": "https://command-not-found.com/pstree"
    },
    "fedora/dnf": {
      "cmd": "sudo dnf install psmisc",
      "reference": "https://command-not-found.com/pstree",
      "dsnap": "psmisc"
    },
    "rhel/dnf": {
      "cmd": "sudo dnf install psmisc",
      "reference": "https://command-not-found.com/pstree"
    },
    "raspbian/apt": {
      "cmd": "sudo apt-get install psmisc",
      "reference": "https://command-not-found.com/pstree"
    }
  },
  "dsnap": {
    "brew": "pstree",
    "yum": "psmisc",
    "pacman": "psmisc",
    "fedora/dnf": "psmisc",
    "alpine/apk": "psmisc",
    "ubuntu/apt": "psmisc",
    "debian/apt": "psmisc"
  }
}
