{	"homepage"	:	"https://github.com/denoland/deno/"	,	"license"	:	"MIT"	,	"source"	:	{	"official"	:	[	"https://dl.deno.land"	]	}	,	"deno_url"	:	"https://dl.deno.land/release"	,	"_os"	:	"%{os}"	,	"_arch"	:	"%{arch}"	,	"download_file_ext"	:	"zip"	,	"url"	:	{	"internet"	:	"%{deno_url}/%{version}/deno-%{_arch}-%{_os}.%{download_file_ext}"	,	"cn"	:	"%{deno_url}/%{version}/deno-%{_arch}-%{_os}.%{download_file_ext}"	}	,	"unpack"	:	"file"	,	"xbin"	:	{	"deno"	:	"shim_bin/deno"	}	,	"sociality"	:	"intrusive"	,	"hook"	:	{	"populate"	:	"populate.sh"	,	"boot"	:	"boot.sh"	,	"unboot"	:	"unboot.sh"	}	,	"path"	:	{	"bin"	:	"shim_bin"	}	,	"env"	:	{	"path"	:	{	"unshift"	:	[	"%{HOME}/.deno/bin"	]	}	}	,	"_build"	:	"0"	,	"tree"	:	"%{os}.%{arch}.%{_build}"	,	"rule"	:	{	"/*"	:	{	"version"	:	"stable"	}	,	"stable/*"	:	{	"version"	:	"v2.2.0"	}	,	"latest/*"	:	{	"version"	:	"v2.2.0"	}	,	"v*/linux/x64"	:	{	"_arch"	:	"x86_64"	,	"_os"	:	"unknown-linux-gnu"	}	,	"v*/linux/arm64"	:	{	"_arch"	:	"aarch64"	,	"_os"	:	"unknown-linux-gnu"	}	,	"v*/darwin/arm64"	:	{	"_arch"	:	"aarch64"	,	"_os"	:	"apple-darwin"	}	,	"v*/darwin/x64"	:	{	"_arch"	:	"x86_64"	,	"_os"	:	"apple-darwin"	}	,	"v*/win/x64"	:	{	"_arch"	:	"x86_64"	,	"_os"	:	"pc-windows-msvc"	}	}	}	