{	"v1.14.0"	:	{	"linux/x64"	:	null	,	"linux/arm64"	:	null	,	"darwin/x64"	:	null	,	"darwin/arm64"	:	null	,	"win/x64"	:	null	}	,	"v1.13.2"	:	{	"linux/x64"	:	null	,	"linux/arm64"	:	null	,	"darwin/x64"	:	null	,	"darwin/arm64"	:	null	,	"win/x64"	:	null	}	,	"v1.13.1"	:	{	"linux/x64"	:	null	,	"linux/arm64"	:	null	,	"darwin/x64"	:	null	,	"darwin/arm64"	:	null	,	"win/x64"	:	null	}	,	"v1.13.0"	:	{	"linux/x64"	:	null	,	"linux/arm64"	:	null	,	"darwin/x64"	:	null	,	"darwin/arm64"	:	null	,	"win/x64"	:	null	}	,	"v1.12.2"	:	{	"linux/x64"	:	null	,	"linux/arm64"	:	null	,	"darwin/x64"	:	null	,	"darwin/arm64"	:	null	,	"win/x64"	:	null	}	}	