{
  "homepage": "https://www.huaweicloud.com/",
  "license": "MIT",
  "bin": "echo",
  "desc": {
    "cn": "华为云命令行工具，提供了一种通过 CLI 调用云服务 API 的方法",
    "en": "HUAWEI cloud Command Line Tool provides a way to call cloud service APIs through the CLI"
  },
  "v4.3.12": {
    "info": {
      "size": {
        "linux/x64": "3.74MB",
        "linux/arm64": "3.19MB",
        "darwin/x64": "7.7MB",
        "darwin/arm64": "7.13MB",
        "win/x64": "8.01MB"
      }
    }
  },
  "v5.1.2": {
    "info": {
      "size": null
    }
  }
}
