{
  "lang": "go",
  "homepage": "https://slimtoolkit.org/",
  "desc": {
    "cn": "Slim 现在是一个 CNCF 沙盒项目，由 Kyle Quest 创建，许多贡献者对它进行了改进",
    "en": "Slim is now a CNCF Sandbox project. It was created by Kyle Quest and it's been improved by many contributors"
  },
  "rule": {
    "/asdf": {
      "cmd": "x asdf use docker-slim",
      "reference": "https://github.com/xataz/asdf-docker-slim"
    },
    "/curl": {
      "cmd": "curl -sL https://raw.githubusercontent.com/slimtoolkit/slim/master/scripts/install-slim.sh | sudo -E bash -",
      "reference": "https://github.com/slimtoolkit/slim?tab=readme-ov-file#scripted-install"
    },
    "darwin/brew": {
      "cmd": "brew install docker-slim",
      "reference": "https://github.com/slimtoolkit/slim?tab=readme-ov-file#homebrew"
    }
  }
}
