{
  "lang": "go",
  "homepage": "https://cli.github.com/",
  "desc": {
    "cn": "GitHub 官方的命令行工具，用于在命令行界面中与 GitHub 进行交互",
    "en": "GitHub's official command line tool is used to interact with GitHub in the Command-line interface"
  },
  "rule": {
    "darwin/brew": {
      "cmd": "brew install gh",
      "reference": "https://formulae.brew.sh/formula/gh#default"
    },
    "darwin/port": {
      "cmd": "sudo port selfupdate && sudo port install gh",
      "reference": "https://github.com/cli/cli#macports"
    },
    "(debian|ubuntu|raspberry)/apt": {
      "cmd": "(type -p wget >/dev/null || (sudo apt update && sudo apt-get install wget -y)) \\\n  && sudo mkdir -p -m 755 /etc/apt/keyrings \\\n  && wget -qO- https://cli.github.com/packages/githubcli-archive-keyring.gpg | sudo tee /etc/apt/keyrings/githubcli-archive-keyring.gpg > /dev/null \\\n  && sudo chmod go+r /etc/apt/keyrings/githubcli-archive-keyring.gpg \\\n  && echo \"deb [arch=$(dpkg --print-architecture) signed-by=/etc/apt/keyrings/githubcli-archive-keyring.gpg] https://cli.github.com/packages stable main\" | sudo tee /etc/apt/sources.list.d/github-cli.list > /dev/null \\\n  && sudo apt update \\\n  && sudo apt install gh -y\n",
      "reference": "https://github.com/cli/cli/blob/trunk/docs/install_linux.md#debian-ubuntu-linux-raspberry-pi-os-apt"
    },
    "(fedora|centos|rhel)/dnf": {
      "cmd": "sudo dnf install gh",
      "reference": "https://github.com/cli/cli/blob/trunk/docs/install_linux.md#fedora-centos-red-hat-enterprise-linux-dnf"
    },
    "alpine/apk": {
      "cmd": "sudo apk add github-cli",
      "reference": "https://github.com/cli/cli/blob/trunk/docs/install_linux.md#alpine-linux"
    },
    "arch/pacman": {
      "cmd": "sudo pacman -S github-cli",
      "reference": "https://github.com/cli/cli/blob/trunk/docs/install_linux.md#arch-linux"
    },
    "opensuse/zypper": {
      "cmd": "sudo zypper addrepo https://cli.github.com/packages/rpm/gh-cli.repo\n&& sudo zypper ref\n&& sudo zypper install gh\n",
      "reference": "https://github.com/cli/cli/blob/trunk/docs/install_linux.md#opensusesuse-linux-zypper"
    },
    "(win|wsl2)/winget": {
      "cmd": "x winget install --id GitHub.cli",
      "reference": "https://github.com/cli/cli#winget"
    },
    "(win|wsl2)/scoop": {
      "cmd": "x scoop install gh",
      "reference": "https://github.com/cli/cli#scoop"
    },
    "(win|wsl2)/choco": {
      "cmd": "x choco install gh",
      "reference": "https://github.com/cli/cli#chocolatey"
    },
    "freebsd/pkg": {
      "cmd": "pkg install gh",
      "reference": "https://github.com/cli/cli/blob/trunk/docs/install_linux.md#freebsd"
    },
    "openbsd/pkg_add": {
      "cmd": "pkg_add github-cli",
      "reference": "https://github.com/cli/cli/blob/trunk/docs/install_linux.md#openbsd"
    },
    "netbsd/pkgsrc": {
      "cmd": "pkgin install gh",
      "reference": "https://github.com/cli/cli/blob/trunk/docs/install_linux.md#netbsdpkgsrc"
    },
    "(funtoo|gentoo)/emerge": {
      "cmd": "sudo emerge -av github-cli",
      "reference": "https://github.com/cli/cli/blob/trunk/docs/install_linux.md#funtoo"
    },
    "kiss/kiss": {
      "cmd": "kiss b github-cli\n&& kiss i github-cli\n",
      "reference": "https://github.com/cli/cli/blob/trunk/docs/install_linux.md#kiss-linux"
    },
    "nix/nixpkgs": {
      "cmd": "nix-env -iA nixos.gh",
      "reference": "https://github.com/cli/cli/blob/trunk/docs/install_linux.md#nixnixos"
    },
    "void/xbps": {
      "cmd": "sudo xbps-install github-cli",
      "reference": "https://github.com/cli/cli/blob/trunk/docs/install_linux.md#void-linux"
    }
  },
  "dsnap": {
    "brew": "gh",
    "choco": "gh",
    "nix": "gh",
    "pacman": "github-cli",
    "pkg": "gh",
    "pkg_add": "github-cli",
    "pkgin": "gh",
    "scoop": "gh",
    "winget": "GitHub.cli",
    "xbps": "github-cli",
    "zypper": "gh",
    "fedora/dnf": "gh"
  }
}
